k3shell/__init__.py
k3shell/command.py
k3shell/synopsis.py
k3shell-0.1.5.dist-info/licenses/LICENSE
k3shell-0.1.5.dist-info/METADATA
k3shell-0.1.5.dist-info/WHEEL
k3shell-0.1.5.dist-info/top_level.txt
k3shell-0.1.5.dist-info/RECORD
